ug/__init__.py
ug/maps.py
ug/util.py
ug-0.0.11.dist-info/LICENSE
ug-0.0.11.dist-info/METADATA
ug-0.0.11.dist-info/WHEEL
ug-0.0.11.dist-info/top_level.txt
ug-0.0.11.dist-info/RECORD
