Metadata-Version: 2.1
Name: ug
Version: 0.0.11
Summary: Utils using Google API
Home-page: https://github.com/thorwhalen/ug
Author: Thor Whalen
License: mit
Platform: any
License-File: LICENSE
Requires-Dist: googlemaps
Requires-Dist: lkj
